<?xml version="1.0" encoding="utf-8"?>
<language xmlns="http://www.pc-axis.scb.se/" name="bs-Latn-BA">
  <sentence name="CtrlCommandBarFunctionChangeTextPresentation" value="Promijenite tekst" />
  <sentence name="CtrlChangeTextsHeading" value="Promijenite tekst" />
  <sentence name="CtrlChangeTextsText" value="Promijenite tekst i  pritisnite dugme Nastavi" />
  <sentence name="CtrlChangeTextsContinueButton" value="Nastavi" />
  <sentence name="CtrlChangeTextsContentsHeading" value="Sadržaj" />
  <sentence name="CtrlChangeTextsUnitsHeading" value="Jedinica" />
  <sentence name="CtrlChangeTextsVariablesHeading" value="Varijabla" />
  <sentence name="CtrlChangePresentationContinueButton" value="Nastavi" />
  <sentence name="CtrlChangePresentationContentsHeading" value="Sadržaj" />
  <sentence name="CtrlChangePresentationUnitsHeading" value="Jedinica" />
  <sentence name="CtrlChangePresentationVariablesHeading" value="Varijabla" />
  <sentence name="CtrlCommandBarFunctionChangeCodeTextPresentation" value="Promijeni tekst/ prezentaciju šifre" />
  <sentence name="CtrlCommandBarFunctionChangeCodeTextHeading" value="Promijeni tekst/ prezentaciju šifre" />
  <sentence name="CtrlChangePresentationChangeCodeTextsText" value="Odaberite opciju za svaku varijablu za koju želite promjenu prezentacije" />
  <sentence name="CtrlChangeCodeTextPresentationText" value="Tekst" />
  <sentence name="CtrlChangeCodeTextPresentationCode" value="Šifra" />
  <sentence name="CtrlChangeCodeTextPresentationCodeAndText" value="Šifra i tekst" />
  <sentence name="CtrlChangeDecimalContinueButton" value="Nastavi" />
  <sentence name="CtrlChangeDecimalHeading" value="Promijeni decimale" />
  <sentence name="CtrlChangeDecimalHeaderLabel" value="Napišite broj decimala koji želite i pritisnite dugme Nastavi" />
  <sentence name="CtrlChangeDecimalDecimalLabel" value="Broj decimala(0-6)" />
  <sentence name="CtrlChangeDecimalRangeError" value="Broj mora biti između 0 i 6" />
  <sentence name="CtrlCommandBarFunctionChangeDecimal" value="Promijeni decimale" />
  <sentence name="CtrlCommandBarFunctionDeleteVariable" value="Izbriši decimale" />
  <sentence name="CtrlDeleteVariableHeaderLabel" value="Označi varijable i vrijednost koja će biti korištena kada je varijabla uklonjena" />
  <sentence name="CtrlDeleteVariableAddToTitleLabel" value="Dodaj vrijednost u naziv tabele" />
  <sentence name="CtrlDeleteVariableContinueButton" value="Nastavi" />
  <sentence name="CtrlDeleteVariableErrorDescription" value="Morate izabrati najmanje jednu varijablu i jednu vrijednost" />
  <sentence name="CtrlDeleteVariableOneVariable" value="Ne možete izbristi sve varijable, najmanje jedna mora ostati" />
  <sentence name="CtrlCommandBarFunctionDeleteValue" value="Izbriši vrijednost" />
  <sentence name="CtrlDeleteValueHeaderLabel" value="Izaberi jednu ili više vrijednosti za brisanje. Ne možete odabrati sve vrijednosti za varijable. Za to morate koristiti Izbriši  varijablu" />
  <sentence name="CtrlDeleteValueErrorDescription" value="Ne možete izbrisati sve vrijednosti  za varijable" />
  <sentence name="CtrlDeleteValueContinueButton" value="Nastavi" />
  <sentence name="CtrlCommandBarFunctionPerPart" value="Procenat" />
  <sentence name="CtrlPerPartContinueButton" value="Nastavi" />
  <sentence name="CtrlPerPartNewValueName" value="Naziv Nove vrijednosti" />
  <sentence name="CtrlPerPartKeepData" value="Prikaži orginalne podatke i procenat" />
  <sentence name="CtrlPerPartPerCentOnly" value="Prikaži samo procenat" />
  <sentence name="CtrlPerPartOneVariableAllValues" value="Odaberite varijablu kao osnovu za izračunavanje procenta" />
  <sentence name="CtrlPerPartOneVariableOneValue" value="Odaberite varijablu za koju ćete odabrati vrijednost kao osnovu" />
  <sentence name="CtrlPerPartOneMatrixValue" value="Odaberite ćelije podataka kao osnovu, jedna vrijednost za svaku varijablu" />
  <sentence name="CtrlCommandBarEditAndCalulateCaption" value="Uredi i Izračunaj" />
  <sentence name="CtrlCommandBarSaveAsCaption" value="Sačuvaj kao" />
  <sentence name="CtrlCommandBarGraphsAndMapsCaption" value="Izgled prezentacije" />
  <sentence name="CtrlCommandBarActionButtonCaption" value="Pošalji" />
  <sentence name="CtrlCommandBarPluginSelectorOkButtonCaption" value="Ok" />
  <sentence name="CtrlCommandBarDownloadFileTitle" value="Sačuvaj datoteku" />
  <sentence name="CtrlCommandBarDownloadFileInformation" value="Kliknite na 'Sačuvaj datoteku' link ispod za preuzimanje datoteke na vaš kompjuter" />
  <sentence name="CtrlCommandBarDownloadFileLink" value="Sačuvaj datoteku" />
  <sentence name="CtrlCommandBarFunctionPivotManual" value="Ručno Pivot " />
  <sentence name="CtrlCommandBarFunctionPivotManualTitle" value="Ručno Pivot " />
  <sentence name="CtrlCommandBarFunctionPivotManualAlt" value="Ručno Pivot " />
  <sentence name="CtrlCommandBarFunctionPivotCW" value="Pivotiraj u smjeru kazaljke na satu" />
  <sentence name="CtrlCommandBarFunctionPivotCWTitle" value="Pivotiraj u smjeru kazaljke na satu" />
  <sentence name="CtrlCommandBarFunctionPivotCWAlt" value="Pivotiraj u smjeru kazaljke na satu" />
  <sentence name="CtrlCommandBarFunctionPivotCCW" value="Pivotiraj suprotno od smjera kretanja kazaljke na satu" />
  <sentence name="CtrlCommandBarFunctionPivotCCWTitle" value="Pivotiraj suprotno od smjera kretanja kazaljke na satu" />
  <sentence name="CtrlCommandBarFunctionPivotCCWAlt" value="Pivotiraj suprotno od smjera kretanja kazaljke na satu" />
  <sentence name="CtrlCommandBarFunctionShowAllRows" value="Prikaži sve redove" />
  <sentence name="CtrlCommandBarFunctionShowAllRowsTitle" value="Prikaži sve redove" />
  <sentence name="CtrlCommandBarFunctionShowAllRowsAlt" value="Prikaži sve redove" />
  <sentence name="CtrlCommandBarFunctionRemoveZero" value="Ukloni redove sa vrijednosti nula" />
  <sentence name="CtrlCommandBarFunctionRemoveZeroTitle" value="Ukloni redove sa vrijednosti nula" />
  <sentence name="CtrlCommandBarFunctionRemoveZeroAlt" value="Ukloni redove sa vrijednosti nula" />
  <sentence name="CtrlCommandBarFunctionRemoveZeroAndHyphen" value="Ukloni redove sa nulom ili '-'" />
  <sentence name="CtrlCommandBarFunctionRemoveZeroAndHyphenTitle" value="Ukloni redove sa nulom ili '-'" />
  <sentence name="CtrlCommandBarFunctionRemoveZeroAndHyphenAlt" value="Ukloni redove sa nulom ili '-'" />
  <sentence name="CtrlCommandBarFunctionRemoveDots" value="Ukloni redove sa tačkama" />
  <sentence name="CtrlCommandBarFunctionRemoveDotsTitle" value="Ukloni redove sa tačkama" />
  <sentence name="CtrlCommandBarFunctionRemoveDotsAlt" value="Ukloni redove sa tačkama" />
  <sentence name="CtrlCommandBarFunctionRemoveZeroHyphenAndDots" value="Ukloni redove sa nulom, '-' ili tačkama" />
  <sentence name="CtrlCommandBarFunctionRemoveZeroHyphenAndDotsTitle" value="Ukloni redove sa nulom, '-' ili tačkama" />
  <sentence name="CtrlCommandBarFunctionRemoveZeroHyphenAndDotsAlt" value="Ukloni redove sa nulom, '-' ili tačkama" />
  <sentence name="CtrlCommandBarFunctionSort" value="Sortiraj" />
  <sentence name="CtrlCommandBarFunctionSortTitle" value="Sortiraj" />
  <sentence name="CtrlCommandBarFunctionSum" value="Saberi vrijednosti varijable" />
  <sentence name="CtrlCommandBarFunctionSumTitle" value="Saberi vrijednosti varijable" />
  <sentence name="CtrlCommandBarFunctionSumAlt" value="Saberi vrijednosti varijable" />
  <sentence name="CtrlCommandBarFunctionSubtract" value="Oduzmi vrijednosti varijabli" />
  <sentence name="CtrlCommandBarFunctionDivide" value="Podijeli vrijednosti varijabli" />
  <sentence name="CtrlCommandBarFunctionMultiply" value="Pomnoži vrijednosti varijabli" />
  <sentence name="CtrlCommandBarFunctionSortAlt" value="Sortiraj" />
  <sentence name="CtrlCommandBarFunctionSwitchLayout" value="Prikaži tabele, novi izgled" />
  <sentence name="CtrlCommandBarFunctionSwitchLayoutAlt" value="Prikaži tabele, novi izgled" />
  <sentence name="CtrlCommandBarFunctionSwitchLayoutTitle" value="Prikaži tabele, novi izgled" />
  <sentence name="CtrlCommandBarFunctionLinkGoogle" value="Google(Testni Link)" />
  <sentence name="CtrlCommandBarFunctionChangeValueOrder" value="Promijeni redosljed vrijednosti" />
  <sentence name="CtrlCommandBarFileTypeXlsTitle" value="Sačuvaj kao Excel" />
  <sentence name="CtrlCommandBarFileTypeXlsAlt" value="Sačuvaj kao Excel" />
  <sentence name="CtrlCommandBarFileTypePxTitle" value="Sačuvaj kao Px" />
  <sentence name="CtrlCommandBarFileTypePXAlt" value="Sačuvaj kao Px" />
  <sentence name="CtrlCommandBarFileTypeTxtTitle" value="Sačuvaj kao Tekst" />
  <sentence name="CtrlCommandBarFileTypeTxtAlt" value="Sačuvaj kao Tekst" />
  <sentence name="CtrlCommandBarFileTypeCsvTitle" value="Sačuvaj kao Csv" />
  <sentence name="CtrlCommandBarFileTypeCsvAlt" value="Sačuvaj kao Csv" />
  <sentence name="CtrlCommandBarFileTypeHtmlTitle" value="Sačuvaj kao Html" />
  <sentence name="CtrlCommandBarFileTypeHtmlAlt" value="Sačuvaj kao Html" />
  <sentence name="CtrlCommandBarFileTypeRelationalTitle" value="Sačuvaj kao Relacionu datoteku" />
  <sentence name="CtrlCommandBarFileTypeRelationallAlt" value="Sačuvaj kao Relacionu datoteku" />
  <sentence name="CtrlPresentationViewTableLayout1" value="Tabela - Izgled 1" />
  <sentence name="CtrlPresentationViewTableLayout2" value="Tabela - Izgled 2" />
  <sentence name="CtrlPresentationViewTableSorted" value="Tabela - Sortirana" />
  <sentence name="CtrlPresentationViewChartColumn" value="Grafikon - Kolona" />
  <sentence name="CtrlPresentationViewChartColumnStacked" value="Grafikon - Posložena kolona" />
  <sentence name="CtrlPresentationViewChartColumnStacked100" value="Grafikon - Posložena kolona 100%" />
  <sentence name="CtrlPresentationViewChartBar" value="Grafikon - Horizontalna kolona" />
  <sentence name="CtrlPresentationViewChartBarStacked" value="Grafikon - Posložena horizontalna kolona" />
  <sentence name="CtrlPresentationViewChartBarStacked100" value="Grafikon - Posložena horizontalna kolona 100%" />
  <sentence name="CtrlPresentationViewChartLine" value="Grafikon - Linija" />
  <sentence name="CtrlPresentationViewChartColumnLine" value="Grafikon - Kolona i linija" />
  <sentence name="CtrlPresentationViewChartPopulationPyramid" value="Kolona - Piramida stanovništva" />
  <sentence name="CtrlPresentationViewChartPie" value="Grafikon - Kružni" />
  <sentence name="CtrlPresentationViewChartArea" value="Grafikon - Područje" />
  <sentence name="CtrlPresentationViewChartAreaStacked" value="Grafikon - Posloženo područje" />
  <sentence name="CtrlPresentationViewChartAreaStacked100" value="Grafikon - Posloženo područje 100%" />
  <sentence name="CtrlPresentationViewChartPoint" value="Grafikon - Tačka" />
  <sentence name="CtrlPresentationViewChartRadar" value="Grafikon - Radar" />
  <sentence name="CtrlCommandBarLinkFootnoteTitle" value="Fusnote" />
  <sentence name="CtrlCommandBarLinkFootnoteAlt" value="Fusnote" />
  <sentence name="CtrlCommandBarLinkGraphTitle" value="Grafikon" />
  <sentence name="CtrlCommandBarLinkGraphAlt" value="Grafikon" />
  <sentence name="CtrlCommandBarLinkInformationTitle" value="Informacije" />
  <sentence name="CtrlCommandBarLinkInformationAlt" value="Informacije" />
  <sentence name="CtrlCommandBarLinkPrintTitle" value="Printaj" />
  <sentence name="CtrlCommandBarLinkPrintAlt" value="Printaj" />
  <sentence name="CtrlCommandBarLinkGoogleTitle" value="Google" />
  <sentence name="CtrlCommandBarLinkGoogleAlt" value="Google" />
  <sentence name="CtrlCommandBarFileDownLoadLink" value="Klikni ovdje za preuzimanje datoteke" />
  <sentence name="CtrlFootnoteFootnoteLabel" value="Fusnote" />
  <sentence name="CtrlFootnoteNoFootnotesLabel" value="Nema fusnota" />
  <sentence name="CtrlHierarchicalVariableSelectAllButton" value="Označi sve" />
  <sentence name="CtrlHierarchicalVariableUnselectAllButton" value="Poništi sve" />
  <sentence name="CtrlHierarchicalVariableOpenAllNodesButton" value="Otvori sve" />
  <sentence name="CtrlHierarchicalVariableCloseAllNodesButton" value="Zatvori sve" />
  <sentence name="CtrlHierarchicalVariableContinueButtonText" value="Nastavi" />
  <sentence name="CtrlHierarchicalVariableErrorMessage" value="Ustanovljena je greška, vratite se na početnu stranicu i ponovo odaberite" />
  <sentence name="CtrlInformationInformationLabel" value="Informacije" />
  <sentence name="CtrlInformationOfficialStatisticsLabel" value="Službene statistike" />
  <sentence name="CtrlInformationUnitLabel" value="Jedinica" />
  <sentence name="CtrlInformationContactLabel" value="Kontakt" />
  <sentence name="CtrlInformationLastUpdatedLabel" value="Posljednja izmjena" />
  <sentence name="CtrlInformationRefPeriodLabel" value="Referentno vrijeme" />
  <sentence name="CtrlInformationStockFaLabel" value="Vrsta podatka" />
  <sentence name="CtrlInformationCFPricesLabel" value="Vrsta cijene" />
  <sentence name="CtrlInformationDayAdjLabel" value="Prilagođen dan" />
  <sentence name="CtrlInformationSeasAdjLabel" value="Sezonski prilagođen" />
  <sentence name="CtrlInformationBasePeriodLabel" value="Osnovno vrijeme" />
  <sentence name="CtrlInformationUpdateFrequencyLabel" value="Frekvencija ažuriranja" />
  <sentence name="CtrlInformationNextUpdateLabel" value="Sljedeće ažuriranje" />
  <sentence name="CtrlInformationSurveyLabel" value="Anketa" />
  <sentence name="CtrlInformationLinkLabel" value="Link" />
  <sentence name="CtrlInformationCreationDateLabel" value="Datum kreiranja" />
  <sentence name="CtrlInformationCopyrightLabel" value="Autorska prava" />
  <sentence name="CtrlInformationSourceLabel" value="Izvor" />
  <sentence name="CtrlInformationMatrixLabel" value="Matrica" />
  <sentence name="CtrlInformationDatabaseLabel" value="Baza podataka" />
  <sentence name="CtrlInformationYesValue" value="Da" />
  <sentence name="CtrlInformationNoValue" value="Ne" />
  <sentence name="CtrlInformationFixedPricesValue" value="Fiksne Cijene" />
  <sentence name="CtrlInformationCurrentPricesValue" value="Tekuće Cijene" />
  <sentence name="CtrlInformationFlowValue" value="Protok" />
  <sentence name="CtrlInformationAverageValue" value="Prosjek" />
  <sentence name="CtrlInformationStockValue" value="Zaliha" />
  <sentence name="CtrlChangeValueOrderInstructionChooseVariable" value="Izaberi varijablu:" />
  <sentence name="CtrlChangeValueOrderInstructionChangeOrder" value="Odaberite redosljed vrijednosti pomicanjem stavke iz jedne liste na drugu. Ako se ne pomjere sve vrijednosti, prvo će biti postavljene vrijednosti iz liste." />
  <sentence name="CtrlChangeValueOrderCancelButton" value="Poništi" />
  <sentence name="CtrlChangeValueOrderContinueButton" value="Nastavi" />
  <sentence name="CtrlChangeValueOrderMoveRight" value="Pomjeri desno" />
  <sentence name="CtrlChangeValueOrderMoveLeft" value="Pomjeri lijevo" />
  <sentence name="CtrlChangeValueOrderMoveDown" value="Pomjeri dole" />
  <sentence name="CtrlChangeValueOrderFromOrder" value="Od reda" />
  <sentence name="CtrlChangeValueOrderToOrder" value="Do reda" />
  <sentence name="CtrlPivotContinueButton" value="Nastavi" />
  <sentence name="CtrlPivotStubLabel" value="Redovi" />
  <sentence name="CtrlPivotHeadingLabel" value="Kolone" />
  <sentence name="CtrlSaveAsSaveTypeListHeadLabel" value="Sačuvaj kao datoteku tipa:" />
  <sentence name="CtrlSaveAsDelimiterListHeadLabel" value="Za razgraničene datoteke, odaberite graničnik:" />
  <sentence name="CtrlSaveAsPageSetupHeadLabel" value="Za tekstualnu datoteku se također odlučite za:" />
  <sentence name="CtrlSaveAsLineLengthControl" value="Dužina linije:" />
  <sentence name="CtrlSaveAsPageLengthControl" value="Dužina stranice:" />
  <sentence name="CtrlSaveAsMarginControl" value="Marginalna" />
  <sentence name="CtrlSaveAsContinueButton" value="Sačuvaj" />
  <sentence name="CtrlSaveAsCancelButton" value="Prekini" />
  <sentence name="CtrlSaveAsButtonLabel" value="Izaberite opciju i pritisnite" />
  <sentence name="CtrlSaveAsSaveTypeDropDown" value="Sačuvaj kao datoteku tipa" />
  <sentence name="CtrlSaveAsDelimiterDropDown" value="Izaberite graničnik" />
  <sentence name="CtrlSaveAsSaveTypeDropDownButton" value="Nastavi" />
  <sentence name="SumInvalidValuename" value="Nova vrijednost mora imati jedinstveni tekst za varijablu." />
  <sentence name="CtrlSumHeading" value="Saberite vrijednosti varijable" />
  <sentence name="CtrlSumTotalVariabelNameText" value="Novo ime vrijednosti:" />
  <sentence name="CtrlSumAllValuesText" value="Saberite sve vrijednosti" />
  <sentence name="CtrlSumSelectedValuesText" value="Saberite odabrane vrijednosti" />
  <sentence name="CtrlSumSelectedVariabelTitle" value="Odaberite vrijednosti za sabiranje" />
  <sentence name="CtrlSumSelectedVariabelValuesTitle" value="Odaberite vrijednosti za sabiranje" />
  <sentence name="CtrlSumVariableNameRequired" value="Naziv za novu vrijednost je obavezan" />
  <sentence name="CtrlSumDifferentOperandsRequired" value="Operacija zahtijeva dva različita operanda." />
  <sentence name="CtrlSumContinueButton" value="Zbir" />
  <sentence name="CtrlSumKeepValuesText" value="Prikaži također originalne vrijednosti" />
  <sentence name="CtrlFirstOperandLabel" value="Prva vrijednost:" />
  <sentence name="CtrlSecondOperandLabel" value="Druga vrijednost:" />
  <sentence name="CtrlSubtractHeading" value="Oduzmi vrijednosti varijable" />
  <sentence name="CtrlSubtractTotalVariabelNameText" value="Unesite tekst za dobivenu vrijednost" />
  <sentence name="CtrlSubtractSelectedVariabelTitle" value="Odaberite varijablu za oduzimanje vrijednosti" />
  <sentence name="CtrlSubtractSelectedVariabelValuesTitle" value="Odaberite 2 vrijednosti za oduzimanje, po željenom redosljedu" />
  <sentence name="CtrlSubtractContinueButton" value="Oduzimanje" />
  <sentence name="CtrlDivideHeading" value="Podijelite vrijednosti varijable" />
  <sentence name="CtrlDivideTotalVariabelNameText" value="Unesite tekst za dobivenu vrijednost" />
  <sentence name="CtrlDivideSelectedVariabelTitle" value="Odaberite varijablu za dijeljenje vrijednosti" />
  <sentence name="CtrlDivideSelectedVariabelValuesTitle" value="Odaberite 2 vrijednosti za dijeljenje, po željenom redosljedu" />
  <sentence name="CtrlDivideErrorSameVariable" value="Dvije iste vrijednosti varijable se ne mogu dijeliti. Odaberite dvije različite varijable." />
  <sentence name="CtrlDivideContinueButton" value="Podijeli" />
  <sentence name="CtrlMultiplyHeading" value="Pomnožite vrijednosti varijabli" />
  <sentence name="CtrlMultiplyTotalVariabelNameText" value="Unesite tekst za dobijenu vrijednost" />
  <sentence name="CtrlMultiplySelectedVariabelTitle" value="Odaberite varijablu za množenje vrijednosti" />
  <sentence name="CtrlMultiplySelectedVariabelValuesTitle" value="Odaberite 2 vrijednosti za množenje" />
  <sentence name="CtrlMultiplyContinueButton" value="Pomnožite" />
  <sentence name="CtrlTableDecimalDelimiter" value="." />
  <sentence name="CtrlTableThousandDelimiter" value="." />
  <sentence name="CtrlTableInformationTableLabel" value="Tabela:" />
  <sentence name="CtrlVariableSelectorInstructionLabel" value="Označite vaš odabir i odaberite između tabele na ekranu i formata datoteke" />
  <sentence name="CtrlVariableSelectorMarkingTipsLink" value="Savjeti za označavanje" />
  <sentence name="CtrlVariableSelectorEliminationTooltip" value="Odaberite najmanje jednu vrijednost" />
  <sentence name="CtrlVariableSelectorSelectValues" value="--- Odaberite klasifikaciju ---" />
  <sentence name="CtrlVariableSelectorEliminationLabel" value="Za varijable koje su obilježene sa {image}, potrebno je odabrati barem jednu vrijednost" />
  <sentence name="CtrlVariableSelectorSelectAllTooltip" value="Izaberite sve" />
  <sentence name="CtrlVariableSelectorDeSelectAllTooltip" value="Poništite sve" />
  <sentence name="CtrlVariableSelectorSortDescTooltip" value="Sortiraj silazno" />
  <sentence name="CtrlVariableSelectorSortAscTooltip" value="Sortiraj uzlazno" />
  <sentence name="CtrlVariableSelectorHierarchicalTooltip" value="Označi hijerarhijski" />
  <sentence name="CtrlVariableSelectorSearchValuesTooltip" value="Traži vrijednost" />
  <sentence name="CtrlVariableSelectorSummaryTotalLabel" value="Ukupno" />
  <sentence name="CtrlVariableSelectorSummarySelectedLabel" value="Izabrano" />
  <sentence name="CtrlVariableSelectorSearchLabel" value="Traži" />
  <sentence name="CtrlVariableSelectorSearchTooltip" value="Traži" />
  <sentence name="CtrlVariableSelectorSearchTextStartCheckBox" value="Početak teksta" />
  <sentence name="CtrlVariableSelectorSelectionLimitsRowsColumnsLabel" value="Prezentacija na ekranu je ograničena na {0} redova i {1} kolona" />
  <sentence name="CtrlVariableSelectorSelectionLimitsCellsLabel" value="Prezentacija na ekranu je ograničena na {0} ćelija" />
  <sentence name="CtrlVariableSelectorSelectionLimitCellsExceeded" value="Broj odabranih ćelija prelazi dozvoljeni maksimum {0}." />
  <sentence name="CtrlVariableSelectorSelectionLimitRowsExceeded" value="Broj odabranih redova prelazi dozvoljeni maksimum {0}." />
  <sentence name="CtrlVariableSelectorSelectionLimitColsExceeded" value="Broj odabranih kolona prelazi dozvoljeni maksimum {0}." />
  <sentence name="CtrlVariableSelectorSelectedRowsLabel" value="Broj odabranih redova podataka" />
  <sentence name="CtrlVariableSelectorSelectedColumnsLabel" value="Broj odabranih kolona podataka" />
  <sentence name="CtrlVariableSelectorSelectedCellsLabel" value="Broj odabranih ćelija podataka je: " />
  <sentence name="CtrlVariableSelectorSelectedCellsLimitLabel" value="(maksimalni dozvoljeni broj je {0})" />
  <sentence name="CtrlVariableSelectorSelectionMissingErrorMessage" value="Najmanje jedna vrijednost mora biti odabrana za varijablu:" />
  <sentence name="CtrlVariableSelectorContinueLabel" value="Odaberite opciju i pritisnite" />
  <sentence name="CtrlVariableSelectorContinueButton" value="Nastavi" />
  <sentence name="CtrlVariableSelectorRowOwerflowMessage" value="Ima više od 500 vrijednosti i one se, zbog toga, automatski ne prikazuju" />
  <sentence name="CtrlVariableSelectorShowAll" value="Pokaži sve" />
  <sentence name="CtrlVariableSelectorShowHierarchy" value="Prikaži hijerarhiju" />
  <sentence name="CtrlVariableSelectorSearch" value="Traži" />
  <sentence name="CtrlVariableSelectorOutputFormatsOutputScreen" value="Prikaži tabelu na ekranu:" />
  <sentence name="CtrlVariableSelectorSearchValuesHeading" value="Traži" />
  <sentence name="CtrlVariableSelectorSearchValuesBeginningOfTextCheckBox" value="Od početka reda" />
  <sentence name="CtrlVariableSelectorManyValues" value="Ima više od {0} vrijednosti i one se, zbog toga, automatski ne prikazuju. Koristite funkciju pretraživanja za odabir vrijednosti." />
  <sentence name="CtrlVariableSelectorLargeValueset" value="(Velika vrijednost postavki)" />
  <sentence name="CtrlVariableSelectorActionButton" value="Pošalji" />
  <sentence name="CtrlCommandBarFunctionSplitTimeVar" value="Razdvoji vremensku varijablu" />
  <sentence name="CtrlSaveQueryCreateHeader" value="Možete sačuvati odabrano za kasniju upotrebu" />
  <sentence name="CtrlSaveQueryCreateDescription" value="Također, možete napraviti jednu ili više izmjena prije nego ih sačuvate." />
  <sentence name="CtrlSaveQueryCreateTableCode" value="Šifra tabele:" />
  <sentence name="CtrlSaveQueryCreateDescriptionLabel" value="Opis:" />
  <sentence name="CtrlSaveQueryCreateHeaderTimeVariable" value="Odaberite vremensku varijablu:" />
  <sentence name="CtrlSaveQueryCreateAlwaysTheSelectedTimePeriod" value="Uvijek odaberite vremenski period/e" />
  <sentence name="CtrlSaveQueryCreateOnlyTheLastTimePeriod" value="Samo zadnji vremenski period" />
  <sentence name="CtrlSaveQueryCreateMovingTimeInterval" value="Promjenljiv vremenski interval (samo za zadnje vremenske periode)" />
  <sentence name="CtrlSaveQueryCreateFixedStartPeriodAndMovingLastPeriod" value="Fiksni početni period i promjenljivi zadnji period" />
  <sentence name="CtrlSaveQueryCreateHeaderPresentation" value="Odaberi prezentaciju:" />
  <sentence name="CtrlSaveQueryCreateTableOnScreen" value="Tabela na ekranu:" />
  <sentence name="CtrlSaveQueryCreateDownloadInFileFormat" value="Preuzimanje datoteke u formatu:" />
  <sentence name="CtrlSaveQueryCreateCreateWebQueryForDataimportInExcel" value="Kreiranje web upita za prebacivanje podataka u Excel" />
  <sentence name="CtrlSaveQueryCreateSendEmailWhenTableIsUpdated" value="Pošalji e-mail kada je tabela ažurirana" />
  <sentence name="CtrlSaveQueryCreateSave" value="Sačuvaj specifikacije tabele" />
  <sentence name="CtrlSaveQueryListEditHeaderStrong" value="Uredi sačuvane specifikacije tabele" />
  <sentence name="CtrlSaveQueryListEditHeaderLine1" value="Ako želite ukloniti sačuvanu specifikaciju tabele, obilježite kvadratić na toj liniji." />
  <sentence name="CtrlSaveQueryListEditHeaderLine2" value="Ako želite promijeniti naziv ili opis tabele, ukucajte novi tekst." />
  <sentence name="CtrlSaveQueryListEditRemove" value="Ukloni" />
  <sentence name="CtrlSaveQueryListEditTableCode" value="Šifra tabele" />
  <sentence name="CtrlSaveQueryListEditDescription" value="Opis" />
  <sentence name="CtrlSaveQueryListEditOutput" value="Izlaz" />
  <sentence name="CtrlSaveQueryListEditUpdate" value="Ažuriranje" />
  <sentence name="CtrlTextSearchButtonText" value="Traži" />
  <sentence name="CtrlTextSearchOptionAll" value="Sve" />
  <sentence name="CtrlTextSearchOptionAnd" value="I" />
  <sentence name="CtrlTextSearchOptionOr" value="Ili" />
  <sentence name="CtrlTextSearchSelect" value="Odaberi dio" />
  <sentence name="CtrlTextSearchDownload" value="Preuzminje završeno" />
  <sentence name="CtrlTextSearchView" value="Vidi tabelu" />
  <sentence name="CtrlTextSearchResultText" value="Traži rezultat za" />
  <sentence name="CtrlTextSearchAttributeModified" value="Promjenjen:" />
  <sentence name="CtrlTextSearchAttributeSize" value="Veličina:" />
  <sentence name="CtrlTableOfContentSizeHeading" value="Veličina:" />
  <sentence name="CtrlTableOfContentSizeKilobytes" value="Kb" />
  <sentence name="CtrlTableOfContentModifiedHeading" value="Promjenjen:" />
  <sentence name="CtrlTableOfContentUpdatedHeading" value="Ažuriran:" />
  <sentence name="CtrlTableOfContentActionButton" value="Javascript je onemogućen, klikni da se napuni cijelo stablo" />
  <sentence name="CtrlTableOfContentExternalLinkTooltip" value="Informacija" />
  <sentence name="CtrlTableListSizeHeading" value="Veličina:" />
  <sentence name="CtrlTableListModifiedHeading" value="Promjenjeno:" />
  <sentence name="CtrlTableListUpdatedHeading" value="Ažurirano:" />
  <sentence name="CtrlTableListVariablesAndValuesHeading" value="Varijable:" />
  <sentence name="CtrlTableListSelectOption_Select" value="Odaberi dio:" />
  <sentence name="CtrlTableListSelectOption_Download" value="Preuzmi:" />
  <sentence name="CtrlTableListSelectOption_Downloadsmallfile" value="Preuzmi:" />
  <sentence name="CtrlTableListSelectOption_View" value="Vidi tabelu:" />
  <sentence name="CtrlTableListSelectOption_ViewDefaultValues" value="Vidi tabelu:" />
  <sentence name="CtrlTableListSelectOption_ViewWithCommandbar" value="Vidi tabelu:" />
  <sentence name="CtrlTableListSelectOption_ViewDefaultValuesWithCommandbar" value="Vidi tabelu:" />
  <sentence name="CtrlCsvFileTypeFileWithHeading" value="Razgraničena datoteka sa naslovom" />
  <sentence name="CtrlCsvFileTypeFileWithoutHeading" value="Razgraničena datoteka bez naslova" />
  <sentence name="CtrlCsvFileTypeFileTabulator" value="Tabulator " />
  <sentence name="CtrlCsvFileTypeFileComma" value="Zarez" />
  <sentence name="CtrlCsvFileTypeFileSpace" value="Prostor" />
  <sentence name="CtrlCsvFileTypeFileSemicolon" value="Tačka-zarez" />
  <sentence name="CtrlExcelInformationLevelNone" value="Nijedno" />
  <sentence name="CtrlExcelInformationLevelMandatoryFootnotes" value="Samo obavezne fusnote" />
  <sentence name="CtrlExcelInformationLevelAllFootnotes" value="Sve fusnote" />
  <sentence name="CtrlExcelInformationLevelAll" value="Sve informacije" />
  <sentence name="CtrlExcelDoubleColumn" value="Šifra i tekst u odvojenim kolonama" />
  <sentence name="FileTypePX" value="PC-Axis datoteka" />
  <sentence name="FileTypeExcel" value="Excel radna knjiga (xml)" />
  <sentence name="FileTypeExcelDoubleColumn" value="Excel radna knjiga (xml) sa šifrom i tekstom" />
  <sentence name="FileTypeExcelCompleteInfoFile" value="Excel datoteka sa ekrana" />
  <sentence name="FileTypeCsvWithHeadingAndTabulator" value="Razgraničeni tabulator sa naslovom" />
  <sentence name="FileTypeCsvWithoutHeadingAndTabulator" value="Razgraničeni tabulator bez naslova" />
  <sentence name="FileTypeCsvWithHeadingAndComma" value="Razgraničeni zarez sa naslovom" />
  <sentence name="FileTypeCsvWithoutHeadingAndComma" value="Razgraničeni zarez bez naslova" />
  <sentence name="FileTypeCsvWithHeadingAndSpace" value="Razgraničeni prostor sa naslovom" />
  <sentence name="FileTypeCsvWithoutHeadingAndSpace" value="Razgraničeni naslov bez naslova" />
  <sentence name="FileTypeCsvWithHeadingAndSemiColon" value="Razgraničeni tačka-zarez sa naslovom" />
  <sentence name="FileTypeCsvWithoutHeadingAndSemiColon" value="Razgraničeni tačka-zarez bez naslova" />
  <sentence name="FileTypeText" value="Tekstualna datoteka(txt)" />
  <sentence name="FileTypeHtml" value="Html datoteka (html)" />
  <sentence name="FileTypeRelational" value="Relaciona datoteka (txt)" />
  <sentence name="FileTypeChartPng" value="Grafikon kao PNG (png)" />
  <sentence name="FileTypeChartGif" value="Grafikon kao Gif (gif)" />
  <sentence name="FileTypeChartJpeg" value="Grafikon kao JPEG (jpg)" />
  <sentence name="FileTypeExcelX" value="Excel (xlsx)" />
  <sentence name="FileTypeExcelXDoubleColumn" value="Excel (xlsx) sa kolonom šifre i teksta" />
  <sentence name="CtrlSearchVariableValuesAddButton" value="Dodaj " />
  <sentence name="CtrlSearchVariableValuesSearchHeader" value="Traži" />
  <sentence name="CtrlSearchVariableValuesSearchForCode" value="Traži šifru:" />
  <sentence name="CtrlSearchVariableValuesSearchForValue" value="Traži tekst:" />
  <sentence name="CtrlSearchVariableValuesSearchTypeBeginning" value="Traži početak šifre/teksta" />
  <sentence name="CtrlSearchVariableValuesSearchTypeAnywhere" value="Traži bilo gdje u tekstu" />
  <sentence name="CtrlSearchVariableValuesSearch" value="Traži" />
  <sentence name="CtrlSearchVariableValuesAddToVariableSelector" value="Dodaj odabrane rezultate" />
  <sentence name="CtrlSearchValuesHeader" value="Traži vrijednosti za" />
  <sentence name="CtrlSearchValuesSearchCode" value="Traži šifru:" />
  <sentence name="CtrlSearchValuesSearchValue" value="Traži vrijednost:" />
  <sentence name="CtrlSearchValuesSearchValueOrCode" value="Traži šifru/vrijednost:" />
  <sentence name="CtrlSearchValuesSearchTypeBeginning" value="Traži početak teksta" />
  <sentence name="CtrlSearchValuesSearchTypeAnywhere" value="Traži bilo gdje u tekstu" />
  <sentence name="CtrlSearchValuesShowAllValues" value="Prikaži sve vrijednosti" />
  <sentence name="CtrlSearchValuesSearch" value="Traži" />
  <sentence name="CtrlSearchValuesSelectionTips" value="Da biste odabrali sve vrijednosti unutar rezultata pretraživanja, kliknite na gornju vrijednost, pritisnite tipku Shift i kliknite na zadnju vrijednost" />
  <sentence name="CtrlSearchValuesSearchResultHeader" value="Traži rezultate" />
  <sentence name="CtrlSearchValuesSearchResultNumberOfHits" value="(broj klikova: {0})" />
  <sentence name="CtrlSearchValuesSearchResultSelectAll" value="Odaberi sve" />
  <sentence name="CtrlSearchValuesChoosenValues" value="Odabrane vrijednosti" />
  <sentence name="CtrlSearchValuesAddToChoosenValues" value="Dodaj odabranu vrijednost" />
  <sentence name="CtrlSearchValuesRemoveFromChoosenValues" value="Ukloni iz odabranih vrijednosti" />
  <sentence name="CtrlSearchValuesNumberOfChoosenValues" value="(broj vrijednosti: {0})" />
  <sentence name="CtrlSearchValuesNoValuesFound" value="Nijedna vrijednost nije pronađena" />
  <sentence name="CtrlSearchValuesNoValuesSelected" value="Nijedna vrijednost nije odabrana" />
  <sentence name="CtrlSearchValuesCancel" value="Poništi" />
  <sentence name="CtrlSearchValuesClear" value="Obriši vrijednosti" />
  <sentence name="CtrlSearchValuesAddToVariableSelector" value="Ok" />
  <sentence name="CtrlSearchValuesSearchLabel" value="Traži" />
  <sentence name="CtrlSearchValuesCode" value="Šifra" />
  <sentence name="CtrlSearchValuesValue" value="Vrijednost" />
  <sentence name="CtrlSearchValuesAllValues" value="Prikaži sve vrijednosti" />
  <sentence name="CtrlSearchValuesSearchText" value="Tekst:" />
  <sentence name="CtrlSearchValuesSearchButton" value="Traži" />
  <sentence name="CtrlSearchValuesPagerFirstPage" value="Prva strana" />
  <sentence name="CtrlSearchValuesPagerNumberOfPages" value="Ukupan broj strana" />
  <sentence name="CtrlSearchValuesPagerLastPage" value="Zadnja strana" />
  <sentence name="CtrlSearchValuesPagerForward" value="Naprijed " />
  <sentence name="CtrlSearchValuesPagerBackward" value="Nazad" />
  <sentence name="CtrlSearchValuesSelectAllAvailableValues" value="Odaberi sve dostupne vrijednosti " />
  <sentence name="PxcYear" value="godina" />
  <sentence name="PxcHalfyear" value="polugodište" />
  <sentence name="PxcQuarter" value="tromjesečje" />
  <sentence name="PxcMonth" value="mjesec" />
  <sentence name="PxcWeek" value="sedmica" />
  <sentence name="PxcMetaTitleBy" value="po " />
  <sentence name="PxcMetaTitleAnd" value="i" />
  <sentence name="PxcOpSplitTimeVarYear" value="godina" />
  <sentence name="PxcOpSplitTimeVarQuarter" value="tromjesečje" />
  <sentence name="PxcOpSplitTimeVarMonth" value="mjesec" />
  <sentence name="PxcOpSplitTimeVarJanuary" value="Januar" />
  <sentence name="PxcOpSplitTimeVarFebruary" value="Februar" />
  <sentence name="PxcOpSplitTimeVarMarch" value="Mart" />
  <sentence name="PxcOpSplitTimeVarApril" value="April" />
  <sentence name="PxcOpSplitTimeVarMay" value="Maj" />
  <sentence name="PxcOpSplitTimeVarJune" value="Juni" />
  <sentence name="PxcOpSplitTimeVarJuly" value="Juli" />
  <sentence name="PxcOpSplitTimeVarAugust" value="August" />
  <sentence name="PxcOpSplitTimeVarSeptember" value="Septembar" />
  <sentence name="PxcOpSplitTimeVarOctober" value="Oktobar" />
  <sentence name="PxcOpSplitTimeVarNovember" value="Novembar" />
  <sentence name="PxcOpSplitTimeVarDecember" value="Decembar" />
  <sentence name="PxcOpSplitTimeVarQuarter1" value="Tromjesečje 1" />
  <sentence name="PxcOpSplitTimeVarQuarter2" value="Tromjesečje 2" />
  <sentence name="PxcOpSplitTimeVarQuarter3" value="Tromjesečje 3" />
  <sentence name="PxcOpSplitTimeVarQuarter4" value="Tromjesečje 4" />
  <sentence name="ERROR_MISSING_TIMEVALUE" value="Nedostaje vremenska vrijednost " />
  <sentence name="PxcErrCellNoteValueMissing" value="Vrijednost={0} nije važeća" />
  <sentence name="PxcErrToManyCodes" value="{0} ima previše specificiranih šifri" />
  <sentence name="PxcGroupedValuesMissing" value="{0} grupisane vrijednosti nedostaju" />
  <sentence name="PxcGroupingVariableWithNoValues" value="Grupisane varijable {0} ne sadrže vrijednosti" />
  <sentence name="PxcSortVariable" value="jedinica varijable" />
  <sentence name="PxcContactPhone" value="Telefon" />
  <sentence name="PxcContactFax" value="Fax" />
  <sentence name="PxcContactEMail" value="e-mail" />
  <sentence name="PxcPercent" value="procent" />
  <sentence name="PxcPermil" value="po kilometraži" />
  <sentence name="PxcPercentUnitVarExists" value="Ne može se izračunati procent kada jedinica varijable već postoji" />
  <sentence name="PxcPermilUnitVarExists" value="Ne može se izračunati po kilometraži kada jedinica varijable već postoji" />
  <sentence name="PxcErr103" value="Greška JEDINICE" />
  <sentence name="PxcErr106" value="Greška TALONA/OGRANKA" />
  <sentence name="PxcErr107" value="Greška NASLOVA" />
  <sentence name="PxcErr108" value="Greška VRIJEDNOSTI" />
  <sentence name="PxcErr109" value="Greška ŠIFRE" />
  <sentence name="PxcErr111" value="NAPOMENA ili NOTEX za grešku varijable " />
  <sentence name="PxcErr112" value="NAPOMENA VRIJEDNOSTI ili VALUENOTEX greška" />
  <sentence name="PxcErr113" value="NAPOMENA ĆELIJE ili CELLNOTEX greška" />
  <sentence name="PxcErr115" value="UKIDANJE da/ne greška" />
  <sentence name="PxcErr117" value="Greška DIJELJENJA" />
  <sentence name="PxcErr121" value="Greška KLJUČEVA" />
  <sentence name="PxcErr123" value="Greška PRECIZNOSTi" />
  <sentence name="PxcErr124" value="Greška DOMENA" />
  <sentence name="PxcErr130" value="NASLOV ili OPIS nedostaje" />
  <sentence name="PxcErr131" value="MATRICA nedostaje" />
  <sentence name="PxcErr132" value="PREDMETNO PODRUČJE nedostaje" />
  <sentence name="PxcErr133" value="PREDMETNA ŠIFRA nedostaje" />
  <sentence name="PxcErr134" value="STUB i NASLOV nedostaju" />
  <sentence name="PxcErr135" value="JEDINICE nedostaju" />
  <sentence name="PxcErr136" value="SADRŽAJI nedostaju" />
  <sentence name="PxcErr137" value="DECIMALE nedostaju " />
  <sentence name="PxcErr138" value="Greška PRIKAZANIH DECIMALA" />
  <sentence name="PxcErr142" value="COPYRIGHT je pogrešan" />
  <sentence name="PxcErr143" value="DAYADJ je pogrešan" />
  <sentence name="PxcErr144" value="SEASADJ je pogrešan" />
  <sentence name="PxcErr146" value="KONTAKT je pogrešan" />
  <sentence name="PxcErr147" value="REF_RAZDOBLJE je pogrešno" />
  <sentence name="PxcErr149" value="ZADNJE AŽURIRANO je pogrešno " />
  <sentence name="PxcErr151" value="STOCKFA je pogrešna" />
  <sentence name="PxcErr152" value="CFPRICES je pogrešan" />
  <sentence name="PxcErr153" value="TIMEVAL je pogreašan" />
  <sentence name="PxcErr154" value="BAZNO_RAZDOBLJE je pogrešno" />
  <sentence name="PxcErr160" value="Ključna riječ koja zavisi o CONTVARIABLE je pronađena, ali varijabla nema sadržaja " />
  <sentence name="PxcErr161" value="Greška CONTVARIABLE ili zavisnosti ključnih riječi" />
  <sentence name="PxcErr162" value="PRESTEXT greška" />
  <sentence name="PxcErr164" value="KARTA greška" />
  <sentence name="PxcErr166" value="AGGREGALLOWED greška" />
  <sentence name="PxcErr167" value="AUTOPEN greška" />
  <sentence name="PxcErr168" value="DUPLA_KOLONA greška" />
  <sentence name="PxcErr169" value="ZADANI_OPIS greška" />
  <sentence name="PxcErr176" value="BILJEŠKA_PODATAKA greška" />
  <sentence name="PxcErr180" value="PODACI nedostaju" />
  <sentence name="PxcErr201" value="OTVORENI_HIJERARHIJSKI_NIVO greška" />
  <sentence name="PxcErr202" value="HIJERARHIJSKI_NIVO greška" />
  <sentence name="PxcErr203" value="HIJERARHIJSKA_IMENA greška" />
  <sentence name="PxcErr204" value="HIJERARHIJA greška" />
  <sentence name="PxcErr205" value="SLUŽBENA_STATISTIKA greška" />
  <sentence name="PxcErr300" value="VRIJEDNOST-TEKST-OPCIJA greška" />
  <sentence name="PxcKeywordError" value="{0} greška" />
  <sentence name="PxcKeywordLastUpdated" value="Zadnje ažuriranje" />
  <sentence name="PxcKeywordSource" value="Izvor" />
  <sentence name="PxcKeywordContact" value="Kontakt" />
  <sentence name="PxcKeywordCopyright" value="Copyright" />
  <sentence name="PxcKeywordUnits" value="Jedinice" />
  <sentence name="PxcKeywordStockfa" value="Vrsta podataka" />
  <sentence name="PxcKeywordStockfaValueStock" value="Zaliha" />
  <sentence name="PxcKeywordStockfaValueFlow" value="Tok" />
  <sentence name="PxcKeywordStockfaValueAverage" value="Prosjek" />
  <sentence name="PxcKeywordRefPeriod" value="Referentni period" />
  <sentence name="PxcKeywordBasePeriod" value="Bazni period" />
  <sentence name="PxcKeywordCFPricesValueCurrent" value="Tekuće cijene" />
  <sentence name="PxcKeywordCFPricesValueFixed" value="Fiksne cijene" />
  <sentence name="PxcKeywordDayAdj" value="Prilagođen dan" />
  <sentence name="PxcKeywordSeasAdj" value="Prilagođena sezona" />
  <sentence name="PxcKeywordDatabase" value="Baza podataka" />
  <sentence name="PxcKeywordMatrix" value="Interna referentna šifra" />
  <sentence name="PXWebSearchLink" value="Traži" />
  <sentence name="PXWebGenXMLLink" value="Generiši izbornik xml" />
  <sentence name="PageViewFootnoteDialogTitle" value="Fusnote" />
  <sentence name="PageViewDataSortDescription" value="Kliknite na naslov kolone za sortiranje tabele. Sortirajte više kolona istovremeno držeći tipku Shift i kliknete na drugo, treće ili čak četvrto zaglavlje kolone" />
  <sentence name="PageViewDataSortCopyInstructions" value="Da biste kopirali tabelu: U izborniku Uredi kliknite na Odaberi sve, a zatim na Kopiraj. Alternativno, pritisnite Ctrl+A i zatim Ctrl+C" />
  <sentence name="CancelButton" value="Poništi" />
  <sentence name="PxWebApplicationTitle" value="BiH-StatBank" />
  <sentence name="PxWebApplicationName" value="Agencija za statistiku Bosne i Hercegovine" />
  <sentence name="PxWebLogoAlt" value="Agencija za statistiku Bosne i Hercegovine" />
  <sentence name="PxWebHome" value="Početna" />
  <sentence name="PxWebMenu" value="Izbornik" />
  <sentence name="PxWebSelection" value="Izbor" />
  <sentence name="PxWebInformation" value="Informacija" />
  <sentence name="PxWebDetailedInformation" value="Detaljne informacije" />
  <sentence name="PxWebFootnotes" value="Fusnote" />
  <sentence name="PxWebMarkingTips" value="Savjeti za označavanje" />
  <sentence name="PxWebMarkingTipsHeader" value="Preporuke za označavanje redova na listi" />
  <sentence name="PxWebMarkingTipsText" value="Potrebno je unijeti bar jednu oznaku u svaku listu kako bi dobili rezultat za svaku varijablu. Ako želite vidjeti samo jednu ili nekoliko&#xD;&#xA;varijabli, označite samo njih. Napomena: ako želite poništiti oznaku, pritisnite tipku CTRL i kliknite mišem na dotičnu oznaku.&#xD;&#xA;&#xD;&#xA;Ako želite odabrati sve redove liste:&#xD;&#xA;- Označite prvi redak liste. Zatim istovremeno pritisnite tipke SHIFT i END.&#xD;&#xA;&#xD;&#xA;Ako želite odabrati/poništiti označeni red liste:&#xD;&#xA;- Istovremeno pritisnite tipku CTRL i kliknite lijevom tipkom miša na odabrani red.&#xD;&#xA;&#xD;&#xA;Ako želite odabrati više redova liste:&#xD;&#xA;- Označite više redova u nizu pritiskom lijeve tipke miša i povlačenjem preko željenih redova. Ili, označite prvi red,&#xD;&#xA;a zatim pritisnite tipku SHIFT i istovremeno na tastaturi strelice za gore/dole.&#xD;&#xA;- Redove koji nisu u nizu označite pritiskom tipke CTRL i istovremeno klikom lijeve tipke miša na željene redove.&#xD;&#xA;&#xD;&#xA;Ako želite pronaći određenu vrijednost u listi:&#xD;&#xA;- Označite prvi red liste. Zatim upišite prvo slovo tražene vrijednosti. Ako ne dobijete traženu vrijednost u prvom pokušaju,&#xD;&#xA;dodajte drugo slovo itd. Možete koristiti i strelice za gore/dole na tastaturi ili miša za daljnje traženje." />
  <sentence name="PxWebPresentation" value="Prezentacija" />
  <sentence name="PxWebTable" value="Tabela" />
  <sentence name="PxWebChart" value="Grafikon" />
  <sentence name="PxWebChartUserSettingsTitle" value="Naslov:" />
  <sentence name="PxWebChartUserSettingsHeight" value="Visina:" />
  <sentence name="PxWebChartUserSettingsWidth" value="Širina:" />
  <sentence name="PxWebChartUserSettingsLineThickness" value="Debljina linije:" />
  <sentence name="PxWebChartUserSettingsSortTime" value="Sortiraj vrijeme:" />
  <sentence name="PxWebChartUserSettingsSortTimeAscending" value="Uzlazni" />
  <sentence name="PxWebChartUserSettingsSortTimeDescending" value="Silazni" />
  <sentence name="PxWebChartUserSettingsSortTimeNone" value="Nijedan" />
  <sentence name="PxWebChartUserSettingsLabelOrientation" value="Orjentacija oznake:" />
  <sentence name="PxWebChartUserSettingsLabelOrientationHorizontal" value="Horizontalno" />
  <sentence name="PxWebChartUserSettingsLabelOrientationVertical" value="Vertikalno " />
  <sentence name="PxWebChartUserSettingsGuidelines" value="Rešetke" />
  <sentence name="PxWebChartUserSettingsGuidelinesHorizontal" value="Horizontalno" />
  <sentence name="PxWebChartUserSettingsGuidelinesVertical" value="Vertikalno" />
  <sentence name="PxWebChartUserSettingsLegend" value="Simbol:" />
  <sentence name="PxWebChartUserSettingsLegendShow" value="Pokaži" />
  <sentence name="PxWebChartUserSettingsLegendHeight" value="Visina (% grafikona)" />
  <sentence name="PxWebChartUserSettingsApply" value="Primijeni" />
  <sentence name="PxWebChartUserSettingsShow" value="Postavke grafikona" />
  <sentence name="PxWebChartUserSettingsHide" value="Sakrij postavke" />
  <sentence name="PxWebChartPieChartTitle" value="Kružni grafikon ne može biti prikazan" />
  <sentence name="PxWebChartPieChartInformation" value="Kružni grafikon može sadržavati samo jednu varijablu sa više od jedne vrijednosti. Koristite operacije 'Obriši varijablu' ili 'Obriši vrijednost' u izborniku 'Uredi i izračunaj' da uklonite varijable i vrijednosti." />
  <sentence name="PxWebChartPyramidChartTitle" value="Piramida stanovništva ne može biti prikazana" />
  <sentence name="PxWebChartPyramidChartInformation" value="Za piramidu stanovništva, jedna od varijabli ima neograničen broj vrijednosti. Jedna od drugih varijabli mora imati dvije vrijednosti, dok ostale varijable mogu imati samo jednu vrijednost. Naprimjer, varijabla Starost može imati sve svoje vrijednosti, a varijabla Spol može imati dvije vrijednosti. Koristite operaciju 'Obriši vrijednost' u izborniku 'Uredi i izračunaj' da uklonite vrijednosti." />
  <sentence name="PxWebChartTooManyValues" value="Previše odabranih vrijednosti" />
  <sentence name="PxWebChartTooManyValuesInformation" value="Odabrali ste previše vrijednosti. Maksimalan broj ćelija u podacima je {0}. Koristite operacije 'Obbriši varijablu' ili 'Izbriši vrijednost' u izborniku 'Uredi i izračunaj'." />
  <sentence name="PxWebChartUserSettingsLargeValue" value="Maksimalna vrijednost je {0}" />
  <sentence name="PxWebChartLeftScale" value="(lijeva skala)" />
  <sentence name="PxWebChartRightScale" value="(desna skala)" />
  <sentence name="PxWebChartPercent" value="%" />
  <sentence name="PxWebDataSort" value="Sortiraj podatke" />
  <sentence name="PxWebSelectDb" value="Odaberite bazu podataka:" />
  <sentence name="PxWebTableCropped" value="Bilješka: Tabela je skraćena. Maksimalno {0} redova i {1} kolona mogu biti prikazane u tabeli na ekranu." />
  <sentence name="PxWebAdminLogout" value="Odjava" />
  <sentence name="PxWebAdminHeading" value="PxWeb Administracija" />
  <sentence name="PxWebAdminVersion" value="PxWeb verzija 2011" />
  <sentence name="PxWebAdminHomePage" value="PxWeb početna stranica" />
  <sentence name="PxWebAdminSaveButton" value="Sačuvaj" />
  <sentence name="PxWebAdminGenerateButton" value="Generiši" />
  <sentence name="PxWebAdminMenuHome" value="Početna" />
  <sentence name="PxWebAdminMenuSettings" value="Postavke" />
  <sentence name="PxWebAdminMenuSettingsGeneral" value="Opći" />
  <sentence name="PxWebAdminMenuSettingsGeneralSite" value="Stranica" />
  <sentence name="PxWebAdminMenuSettingsGeneralLanguage" value="Jezik" />
  <sentence name="PxWebAdminMenuSettingsGeneralPaths" value="Putevi" />
  <sentence name="PxWebAdminMenuSettingsGeneralFileFormats" value="Formati datoteka" />
  <sentence name="PxWebAdminMenuSettingsGeneralModules" value="Moduli" />
  <sentence name="PxWebAdminMenuSettingsGeneralGlobal" value="Globalni" />
  <sentence name="PxWebAdminMenuSettingsGeneralDatabases" value="Baze podataka" />
  <sentence name="PxWebAdminMenuSettingsGeneralAdministration" value="Administracija" />
  <sentence name="PxWebAdminMenuSettingsMenu" value="Izbornik" />
  <sentence name="PxWebAdminMenuSettingsSelection" value="Odabir" />
  <sentence name="PxWebAdminMenuSettingsPresentation" value="Prezentacija" />
  <sentence name="PxWebAdminMenuSettingsPresentationGeneral" value="Opći" />
  <sentence name="PxWebAdminMenuSettingsPresentationTable" value="Tabela" />
  <sentence name="PxWebAdminMenuSettingsPresentationCommandBar" value="Naredbeni bar" />
  <sentence name="PxWebAdminMenuTools" value="Alati" />
  <sentence name="PxWebAdminMenuToolsGenerateDb" value="Generiši bazu podataka" />
  <sentence name="PxWebAdminMenuToolsLanguageManager" value="Upravitelj jezika" />
  <sentence name="PxWebAdminMenuToolsReset" value="Resetuj" />
  <sentence name="PxWebAdminMenuToolsChangePassword" value="Promijeni lozinku" />
  <sentence name="PxWebAdminMenuFeatures" value="Obilježja" />
  <sentence name="PxWebAdminMenuFeaturesGeneral" value="Opći" />
  <sentence name="PxWebAdminMenuFeaturesCharts" value="Grafikon" />
  <sentence name="PxWebAdminMenuFeaturesChartsGeneral" value="Opći" />
  <sentence name="PxWebPxLogin" value="PxWeb prijava" />
  <sentence name="PxWebLogin" value="Prijava" />
  <sentence name="PxWebUsername" value="Korisničko ime" />
  <sentence name="PxWebPassword" value="Lozinka" />
  <sentence name="PxWebWrongLogin" value="Pogrešno korisničko ime ili lozinka" />
  <sentence name="PxWebAdminSettingsDatabasesPxDatabases" value="PX baze podataka" />
  <sentence name="PxWebAdminSettingsDatabasesPxDatabasesInfo" value="Odabrana PX baza podataka će biti prikazana na PxWebu" />
  <sentence name="PxWebAdminSettingsDatabasesCnmmDatabases" value="CNMM (Zajednički nordijski metamodel) baze podataka" />
  <sentence name="PxWebAdminSettingsDatabasesCnmmDatabasesInfo" value="Odabrane CNMM baze podataka će biti prikazane na PxWebu" />
  <sentence name="PxWebAdminSettingsPathsLanguagePath" value="Put jezika" />
  <sentence name="PxWebAdminSettingsPathsLanguagePathInfo" value="Put do direktorija koji sadrži jezične datoteke" />
  <sentence name="PxWebAdminSettingsPathsImagePath" value="Put slike" />
  <sentence name="PxWebAdminSettingsPathsImagePathInfo" value="Put do direktorija koji sadrži slike" />
  <sentence name="PxWebAdminSettingsPathsPxDatabasePath" value="Put PX baza podataka" />
  <sentence name="PxWebAdminSettingsPathsPxDatabasePathInfo" value="Put do direktorija koji sadrži PX baze podataka" />
  <sentence name="PxWebAdminSettingsPathsAggregationPath" value="Put agregacije" />
  <sentence name="PxWebAdminSettingsPathsAggregationPathInfo" value="Put do direktorija koji sadrži agregacijske datoteke" />
  <sentence name="PxWebAdminSettingsFileFormatsCellLimitDownload" value="Preuzimanje ograničenog broja ćelija " />
  <sentence name="PxWebAdminSettingsFileFormatsCellLimitDownloadInfo" value="Maksimalni broj preuzetih ćelija u rezultirajućoj tabeli" />
  <sentence name="PxWebAdminSettingsFileFormatsExcel" value="Excel" />
  <sentence name="PxWebAdminSettingsFileFormatsExcelInformationLevel" value="Informacioni nivo" />
  <sentence name="PxWebAdminSettingsFileFormatsExcelInformationLevelInfo" value="Kontroliše koje se informacije prikazuju u Excel datoteci" />
  <sentence name="PxWebAdminSettingsFileFormatsExcelInformationLevelNone" value="Nijedan" />
  <sentence name="PxWebAdminSettingsFileFormatsExcelInformationLevelMandantoryFootnotesOnly" value="Samo obavezne fusnote" />
  <sentence name="PxWebAdminSettingsFileFormatsExcelInformationLevelAllFootnotes" value="Sve fusnote" />
  <sentence name="PxWebAdminSettingsFileFormatsExcelInformationLevelAllInformation" value="Sve informacije" />
  <sentence name="PxWebAdminSettingsFileFormatsExcelDoubleColumn" value="Duple kolone" />
  <sentence name="PxWebAdminSettingsFileFormatsExcelDoubleColumnInfo" value="Ako će šifra uvijek biti prikazana u odvojenim kolonama" />
  <sentence name="PxWebAdminSettingsGlobalSecrecyOption" value="Opcija Tajnosti" />
  <sentence name="PxWebAdminSettingsGlobalSecrecyOptionInfo" value="Ako vrijednosti podataka trebaju biti obfuscated kada su prikazane" />
  <sentence name="PxWebAdminSettingsGlobalSecrecyOptionNone" value="Nijedan " />
  <sentence name="PxWebAdminSettingsGlobalSecrecyOptionSimple" value="Jednostavan" />
  <sentence name="PxWebAdminSettingsGlobalRoundingRule" value="Pravilo zaokruživanja" />
  <sentence name="PxWebAdminSettingsGlobalRoundingRuleBankersRounding" value="Bankarsko zaokruživanje" />
  <sentence name="PxWebAdminSettingsGlobalRoundingRuleRoundUp" value="Zaokružiti na gore" />
  <sentence name="PxWebAdminSettingsGlobalRoundingRuleInfo" value="Vrsta pravila zaokruživanja ('Bankarsko zaokruživanje' ili 'Zaokruživanje na gore')" />
  <sentence name="PxWebAdminSettingsGlobalSymbol1" value="Simbol 1" />
  <sentence name="PxWebAdminSettingsGlobalSymbol1Info" value="Tekst za prikaz za mjere koje imaju Podatkovni Simbol 1" />
  <sentence name="PxWebAdminSettingsGlobalSymbol2" value="Simbol 2" />
  <sentence name="PxWebAdminSettingsGlobalSymbol2Info" value="Tekst za prikaz za mjere koje imaju Podatkovni Simbol 2" />
  <sentence name="PxWebAdminSettingsGlobalSymbol3" value="Simbol 3" />
  <sentence name="PxWebAdminSettingsGlobalSymbol3Info" value="Tekst za prikaz za mjere koje imaju Podatkovni Simbol 3" />
  <sentence name="PxWebAdminSettingsGlobalSymbol4" value="Sibmol 4" />
  <sentence name="PxWebAdminSettingsGlobalSymbol4Info" value="Tekst za prikaz za mjere koje imaju Podatkovni Simbol 4" />
  <sentence name="PxWebAdminSettingsGlobalSymbol5" value="Simbol 5" />
  <sentence name="PxWebAdminSettingsGlobalSymbol5Info" value="Tekst za prikaz za mjere koje imaju Podatkovni Simbol 5" />
  <sentence name="PxWebAdminSettingsGlobalSymbol6" value="Simbol 6" />
  <sentence name="PxWebAdminSettingsGlobalSymbol6Info" value="Tekst za prikaz za mjere koje imaju Podatkovni Simbol 6" />
  <sentence name="PxWebAdminSettingsGlobalDataSymbolNil" value="Podatkovni Simbol NIL" />
  <sentence name="PxWebAdminSettingsGlobalDataSymbolNilInfo" value="Tekst za prikaz za mjere koje imaju Podatovni Simbol NIL" />
  <sentence name="PxWebAdminSettingsGlobalDataSymbolSum" value="Podatkovni Simbol Zbir" />
  <sentence name="PxWebAdminSettingsGlobalDataSymbolSumInfo" value="Tekst za prikaz za mjere koje imaju Podatkovni Simbol Zbir " />
  <sentence name="PxWebAdminSettingsGlobalShowSourceDescription" value="Pokaži opis izvora" />
  <sentence name="PxWebAdminSettingsGlobalShowSourceDescriptionInfo" value="Da li će opis izvora biti prikazan za tabelu ili ne" />
  <sentence name="PxWebAdminSettingsGlobalTableInformationLevel" value="Tabela nivoa informacije" />
  <sentence name="PxWebAdminSettingsGlobalTableInformationLevelInfo" value="Kontrola za informaciju koja je prikazana u tabeli" />
  <sentence name="PxWebAdminSettingsGlobalTableInformationLevelNone" value="Nijedan" />
  <sentence name="PxWebAdminSettingsGlobalTableInformationLevelMandantoryFootnotesOnly" value="Samo obavezne fusnote" />
  <sentence name="PxWebAdminSettingsGlobalTableInformationLevelAllFootnotes" value="Sve fusnote" />
  <sentence name="PxWebAdminSettingsGlobalTableInformationLevelAllInformation" value="Sve informacije" />
  <sentence name="PxWebAdminSettingsGlobalUpperCase" value="Velika slova" />
  <sentence name="PxWebAdminSettingsGlobalUpperCaseInfo" value="Pravilo početnog velikog slova u nazivu vrijednosti" />
  <sentence name="PxWebAdminSettingsGlobalDataNotePlacement" value="Položaj Bilješke podataka" />
  <sentence name="PxWebAdminSettingsGlobalDataNotePlacementInfo" value="Određivanje položaja bilježaka podataka. Bilješke podataka mogu biti smještene ispred ili iza vrijednosti" />
  <sentence name="PxWebAdminSettingsGlobalDataNotePlacementBeforeValue" value="Ispred vrijednosti" />
  <sentence name="PxWebAdminSettingsGlobalDataNotePlacementAfterValue" value="Iza vrijednosti" />
  <sentence name="PxWebAdminSettingsGlobalRemoveSingleContent" value="Ukloni jedan sadržaj" />
  <sentence name="PxWebAdminSettingsGlobalRemoveSingleContentInfo" value="Ukloni sadržaj varijable ako sadrži samo jednu vrijednost" />
  <sentence name="PxWebAdminSettingsGlobalShowInformationTypes" value="Prikaži vrste informacija" />
  <sentence name="PxWebAdminSettingsGlobalShowInformationTypesInfo" value="Koje vrste informacija će biti prikazane u tabelama informacija" />
  <sentence name="PxWebAdminSettingsAdministrationUseIPFilter" value="Koristi IP filter" />
  <sentence name="PxWebAdminSettingsAdministrationUseIPFilterInfo" value="Da li će se koristiti IP filter prilikom prijave na stranicu administratora ili ne" />
  <sentence name="PxWebAdminSettingsAdministrationIPAddresses" value="IP adrese" />
  <sentence name="PxWebAdminSettingsAdministrationIPAddressesInfo" value="Popis IP adresa s dozvolom za pristup administracijskim stranicama. Ova postavka vrijedi samo ako je postavka &quot;Koristi IP Filter ' postavljena kao Tačno." />
  <sentence name="PxWebAdminSettingsAdministrationAddNewIPAddress" value="Dodaj novu IP adresu" />
  <sentence name="PxWebAdminSettingsAdministrationInvalidIPAddress" value="Nevažeća IP adresa" />
  <sentence name="PxWebAdminSettingsMenuMenuMode" value="Metoda Izbornika" />
  <sentence name="PxWebAdminSettingsMenuMenuModeInfo" value="Kontrole prikazivanja Izbornika" />
  <sentence name="PxWebAdminSettingsMenuMenuModeList" value="Lista" />
  <sentence name="PxWebAdminSettingsMenuMenuModeTreeViewWithoutFiles" value="Prikaz strukture bez datoteka" />
  <sentence name="PxWebAdminSettingsMenuMenuModeTreeViewWithFiles" value="Prikaz strukture sa datotekama" />
  <sentence name="PxWebAdminSettingsMenuMenuModeTreeViewAndFiles" value="Prikaz strukture i datoteka" />
  <sentence name="PxWebAdminSettingsMenuShowRoot" value="Prikaži korijen" />
  <sentence name="PxWebAdminSettingsMenuShowRootInfo" value="Da li će čvor korijena biti prikazan ili ne?" />
  <sentence name="PxWebAdminSettingsMenuExpandAll" value="Proširi sve" />
  <sentence name="PxWebAdminSettingsMenuExpandAllInfo" value="Da li će struktura biti proširena ili  ne?" />
  <sentence name="PxWebAdminSettingsMenuSortByAlias" value="Sortiraj po pseudonimima" />
  <sentence name="PxWebAdminSettingsMenuSortByAliasInfo" value="Da li će čvorovi biti razvrstani po pseudonimima ili ne?" />
  <sentence name="PxWebAdminSettingsMenuShowSelectionLink" value="Prikaži odabrani link" />
  <sentence name="PxWebAdminSettingsMenuShowSelectionLinkInfo" value="Da li će link na stranici na kojoj korisnik bira varijable biti prikazan ili ne?" />
  <sentence name="PxWebAdminSettingsMenuShowDownloadLink" value="Prikaži preuzeti link" />
  <sentence name="PxWebAdminSettingsMenuShowDownloadLinkInfo" value="Da li će link kojim korisnik preuzima tabele kao datoteke biti prikazan ili ne?" />
  <sentence name="PxWebAdminSettingsMenuShowDownloadLinkAlwaysHide" value="Uvijek sakrij" />
  <sentence name="PxWebAdminSettingsMenuShowDownloadLinkAlwaysShow" value="Uvijek prikaži" />
  <sentence name="PxWebAdminSettingsMenuShowDownloadLinkShowIfSmallFile" value="Prikaži ako je datoteka mala" />
  <sentence name="PxWebAdminSettingsMenuViewLinkMode" value="Način za Pregled_linka" />
  <sentence name="PxWebAdminSettingsMenuViewLinkModeInfo" value="Način za Pregled linka. Može imati jednu od tri različite vrijednosti: 'Početne vrijednosti'= Početne vrijednosti su prikazane u tabeli kada korisnik klikne na link. 'Sve vrijednosti'= Sve vrijednosti su prikazane unutar tabele kada korisnik klikne na link. 'Sakriveno'= Link nije prikazan." />
  <sentence name="PxWebAdminSettingsMenuViewLinkModeDefaultValues" value="Početne vrijednosti" />
  <sentence name="PxWebAdminSettingsMenuViewLinkModeAllValues" value="Sve vrijednosti" />
  <sentence name="PxWebAdminSettingsMenuViewLinkModeHidden" value="Sakriveno" />
  <sentence name="PxWebAdminSettingsMenuNumberOfValuesInDefaultView" value="Broj početnih vrijednosti" />
  <sentence name="PxWebAdminSettingsMenuNumberOfValuesInDefaultViewInfo" value="Maksimalan broj vrijednosti koje su odabrane kada je Viewlink = 'Početne vrijednosti'. Vrijednosti su unaprijed odabrane umjesto da korisnici odabiraju varijable i vrijednosti." />
  <sentence name="PxWebAdminSettingsMenuShowModifiedDate" value="Prikaži izmijenjeni datum" />
  <sentence name="PxWebAdminSettingsMenuShowModifiedDateInfo" value="Da li će izmijenjeni datum biti prikazan ili ne" />
  <sentence name="PxWebAdminSettingsMenuShowLastUpdated" value="Prikaži zadnje ažurirano" />
  <sentence name="PxWebAdminSettingsMenuShowLastUpdatedInfo" value="Da li će informacija o zadnjem ažuriranju biti prikazana ili ne" />
  <sentence name="PxWebAdminSettingsMenuShowFileSize" value="Prikaži veličinu datoteke" />
  <sentence name="PxWebAdminSettingsMenuShowFileSizeInfo" value="Da li će informacija o veličini datoteke biti prikazana ili ne" />
  <sentence name="PxWebAdminSettingsMenuShowVariablesAndValues" value="Prikaži varijable i vrijednosti" />
  <sentence name="PxWebAdminSettingsMenuShowVariablesAndValuesInfo" value="Da li će informacija o varijablama i vrijednostima unutar tabele biti prikazana ili ne" />
  <sentence name="PxWebAdminSettingsSelectionCellLimitScreen" value="Ekran ograničenog broja ćelija " />
  <sentence name="PxWebAdminSettingsSelectionCellLimitScreenInfo" value="Maksimalan broj ćelija koji može biti prikazan na ekranu" />
  <sentence name="PxWebAdminSettingsSelectionShowMandatoryMark" value="Prikaži obaveznu oznaku" />
  <sentence name="PxWebAdminSettingsSelectionShowMandatoryMarkInfo" value="Da li obavezne varijable moraju biti označene ili ne" />
  <sentence name="PxWebAdminSettingsSelectionAllowAggregations" value="Dopustite agregacije" />
  <sentence name="PxWebAdminSettingsSelectionAllowAggregationsInfo" value="Da li će agregacije vrijednosti varijabli biti moguće ili ne" />
  <sentence name="PxWebAdminSettingsSelectionShowHierarchies" value="Prikaži hijerarhije" />
  <sentence name="PxWebAdminSettingsSelectionShowHierarchiesInfo" value="Da li će hijerarhije biti prikazane ili ne" />
  <sentence name="PxWebAdminSettingsSelectionHierarchicalLevelsOpen" value="Otvoreni hijerarhijski nivoi" />
  <sentence name="PxWebAdminSettingsSelectionHierarchicalLevelsOpenInfo" value="Određuje kako će proširena hijerarhija biti zadana" />
  <sentence name="PxWebAdminSettingsSelectionShowMarkingTips" value="Prikaži savjete za označavanje" />
  <sentence name="PxWebAdminSettingsSelectionShowMarkingTipsInfo" value="Da li će savjeti za označavanje biti prikazani ili ne" />
  <sentence name="PxWebAdminSettingsSelectionMarkingTipsURL" value="Savjeti za označavanje URL" />
  <sentence name="PxWebAdminSettingsSelectionMarkingTipsURLInfo" value="URL za web-stranicu sa savjetima za označavanje" />
  <sentence name="PxWebAdminSettingsSelectionMaxRowsWithoutSearch" value="Maksimalni redovi bez traženja" />
  <sentence name="PxWebAdminSettingsSelectionMaxRowsWithoutSearchInfo" value="Maksimalne vrijednsti za varijable su prikazane na izborniku. Ako varijabla ima više vrijednosti, korisnik mora koristiti funkciju Traži za odabir vrijednosti." />
  <sentence name="PxWebAdminSettingsSelectionListSize" value="Veličina liste" />
  <sentence name="PxWebAdminSettingsSelectionListSizeInfo" value="Broj redova (visina)u izborniku varijable" />
  <sentence name="PxWebAdminSettingsSelectionShowSelectionLimits" value="Prikaži ograničenja odabira" />
  <sentence name="PxWebAdminSettingsSelectionShowSelectionLimitsInfo" value="Da li će informacija o ograničenjima odabira biti prikazana ili ne" />
  <sentence name="PxWebAdminSettingsSelectionOutputFormats" value="Izlazni formati" />
  <sentence name="PxWebAdminSettingsSelectionOutputFormatsInfo" value="Odabrani izlazni formati (pregledi prezentacija i formata datoteka) će biti dostupni za odabir u PxWeb" />
  <sentence name="PxWebAdminSettingsSelectionPresentationViews" value="Pregledi prezentacije:" />
  <sentence name="PxWebAdminSettingsSelectionFileFormats" value="Formati datoteke:" />
  <sentence name="PxWebAdminSettingsSelectionValuesetMustBeSelectedFirst" value="Set vrijednosti mora biti odabran" />
  <sentence name="PxWebAdminSettingsSelectionValuesetMustBeSelectedFirstInfo" value="Ako varijabla ima set vrijednosti, korisnik mora odabrati set vrijednosti prije vrijednosti kada su postavke podešene na Tačno" />
  <sentence name="PxWebAdminSettingsSelectionShowAllAvailableValuesSearchButton" value="Prikaži 'Sve dostupne vrijednosti'" />
  <sentence name="PxWebAdminSettingsSelectionShowAllAvailableValuesSearchButtonInfo" value="Ako 'Prikaži sve dostupne vrijednosti' u tražilici prikaže: 'Upozorenje!', ova postavka može rezultirati velikim web stranicama koje mogu biti teške za učitavanje." />
  <sentence name="PxWebAdminSettingsSelectionSearchButtonMode" value="Način rada funkcije Traženja " />
  <sentence name="PxWebAdminSettingsSelectionSearchButtonModeManyValues" value="Višestruke vrijednosti" />
  <sentence name="PxWebAdminSettingsSelectionSearchButtonModeAlways" value="Uvijek" />
  <sentence name="PxWebAdminSettingsSelectionSearchButtonModeInfo" value="Kontrola kada će dugme za pretraživanje vrijednosti biti prikazano" />
  <sentence name="PxWebAdminSettingsValidationMandatorySetting" value="Obavezno polje" />
  <sentence name="PxWebAdminSettingsValidationNonexistentPath" value="Put ne postoji" />
  <sentence name="PxWebAdminSettingsValidationNonexistentImage" value="Slika ne postoji" />
  <sentence name="PxWebAdminSettingsValidationIntegerValue" value="Mora biti cjelobrojna vrijednost" />
  <sentence name="PxWebAdminSettingsValidationTooLargeIntegerValue" value="Ne može biti veća od 2147483647" />
  <sentence name="PxWebAdminSettingsValidationGreaterThanZero" value="Vrijednost mora biti veća od 0" />
  <sentence name="PxWebAdminSettingsValidationIllegalCharacter" value="Sadrži nedopušteni znak" />
  <sentence name="PxWebAdminSettingsValidationBiggerThanMaxSetting" value="Ne može biti veća od maksimalne postavke ({0})" />
  <sentence name="PxWebAdminSettingsValidationMaximumValue" value="Maksimalna vrijednost je {0}" />
  <sentence name="PxWebAdminSettingsValidationIllegalColorCode" value="Nedopuštena šifra boje (očekivani format je #AAAAAA)" />
  <sentence name="PxWebAdminSettingsPresentationCommandBarHeaderOperations" value="Operacije" />
  <sentence name="PxWebAdminSettingsPresentationCommandBarHeaderOperationsInfo" value="Odabrane operacije će biti dostupne  korisniku PxWeb" />
  <sentence name="PxWebAdminSettingsPresentationCommandBarHeaderFileformats" value="Formati datoteka" />
  <sentence name="PxWebAdminSettingsPresentationCommandBarHeaderFileformatsInfo" value="Odabrani formati datoteka će biti dostupni korisniku PxWeb" />
  <sentence name="PxWebAdminSettingsPresentationCommandBarHeaderButton" value="Dugme" />
  <sentence name="PxWebAdminSettingsPresentationCommandBarHeaderButtonInfo" value="Odabrane operacije će biti dostupne  korisniku PxWeb" />
  <sentence name="PxWebAdminSettingsPresentationCommandBarHeaderShortcut" value="Prečica" />
  <sentence name="PxWebAdminSettingsPresentationCommandBarHeaderShortcutInfo" value="O prečici" />
  <sentence name="PxWebAdminSettingsPresentationCommandBarHeaderPresentationViews" value="Pregledi prezentacija" />
  <sentence name="PxWebAdminSettingsPresentationCommandBarHeaderPresentationViewsInfo" value="Odabrane prezentacije će biti dostupne korisniku PxWeb" />
  <sentence name="PxWebAdminSettingsPresentationCommandBarViewModeText" value="Način rada preglednika" />
  <sentence name="PxWebAdminSettingsPresentationCommandBarViewModeDropDown" value="Padajući" />
  <sentence name="PxWebAdminSettingsPresentationCommandBarViewModeImageButtons" value="Dugme" />
  <sentence name="PxWebAdminSettingsPresentationCommandBarViewModeHidden" value="Skriveni" />
  <sentence name="PxWebAdminSettingsPresentationCommandBarHeaderSetting" value="Operacija" />
  <sentence name="PxWebAdminSettingsPresentationCommandBarHeaderDropDown" value="Padajući" />
  <sentence name="PxWebAdminSettingsPresentationCommandBarHeaderButton2" value="Dugme" />
  <sentence name="PxWebAdminSettingsPresentationCommandBarHeaderOperationShortcut" value="Prečica" />
  <sentence name="PxWebAdminSettingsPresentationCommandBarHeaderPresentationView" value="Pregled prezentacije" />
  <sentence name="PxWebAdminSettingsPresentationCommandBarHeaderPresentationViewShortcut" value="Prečica" />
  <sentence name="PxWebAdminSettingsPresentationCommandBarHeaderCommandbarShortcut" value="Linija za naredbe za prečicu" />
  <sentence name="PxWebAdminSettingsPresentationCommandBarHeaderFileFormat" value="Format datoteke" />
  <sentence name="PxWebAdminSettingsPresentationCommandBarHeaderFileFormatDropDown" value="Padajući" />
  <sentence name="PxWebAdminSettingsPresentationCommandBarHeaderFileFormatShortcut" value="Prečica" />
  <sentence name="PxWebAdminSettingsPresentationGeneralPromptNotes" value="Odziv za obavezne fusnote" />
  <sentence name="PxWebAdminSettingsPresentationGeneralPromptNotesInfo" value="Da li će obavezne fusnote biti dostupne korisniku kada je tabela prikazana" />
  <sentence name="PxWebAdminSettingsPresentationTableTransform" value="Transformacija tabele" />
  <sentence name="PxWebAdminSettingsPresentationTableTransformInfo" value="Da li će tabela biti automatski transformisana prije nego je prikazana korisniku" />
  <sentence name="PxWebAdminSettingsPresentationTableTransformNoTransformation" value="Nema transformacije" />
  <sentence name="PxWebAdminSettingsPresentationTableTransformSingleValueFirst" value="Prvo pojedinačne vrijednosti" />
  <sentence name="PxWebAdminSettingsPresentationTableTransformSingleValueFirstAndHeaderOnlyOneMultiple" value="Samo jedna viševrijednosna varijabla u zaglavlju" />
  <sentence name="PxWebAdminSettingsPresentationDefaultLayout" value="Početni izgled" />
  <sentence name="PxWebAdminSettingsPresentationDefaultLayoutInfo" value="Početni izgled za prikaz tabela korisniku" />
  <sentence name="PxWebAdminSettingsPresentationDefaultLayoutLayout1" value="Izgled 1" />
  <sentence name="PxWebAdminSettingsPresentationDefaultLayoutLayout2" value="Izgled 2" />
  <sentence name="PxWebAdminSettingsPresentationTableMaxRows" value="Maksimalni redovi" />
  <sentence name="PxWebAdminSettingsPresentationTableMaxRowsInfo" value="Maksimalan broj redova koji će biti prikazani u tabeli na ekranu. Ako temeljni podaci tabela sadrže više redova nego što je navedeno u ovom okruženju, tabela na ekranu će biti skraćena." />
  <sentence name="PxWebAdminSettingsPresentationTableMaxColumns" value="Maksimalne kolone" />
  <sentence name="PxWebAdminSettingsPresentationTableMaxColumnsInfo" value="Maksimalan broj kolona koji će biti prikazan u tabeli na zaslonu. Ako temeljni podaci tabela sadrže više kolona nego što je navedeno u ovom okruženju, tabela na zaslonu će biti skraćena." />
  <sentence name="PxWebAdminSettingsPresentationTableTitleVisible" value="Prikaži naslov" />
  <sentence name="PxWebAdminSettingsPresentationTableTitleVisibleInfo" value="Da li će naslov tabele biti prikazan unutar tabele ili ne" />
  <sentence name="PxWebAdminToolsGenerateDbSelectDb" value="Generiši PX bazu podataka" />
  <sentence name="PxWebAdminToolsGenerateCnmmDbSelectDb" value="Generiši CNMM baze podataka" />
  <sentence name="PxWebAdminToolsGenerateDbSelectDbInfo" value="Odaberite jednu od baza podataka da biste generisali datoteku sa njenim opisom" />
  <sentence name="PxWebAdminToolsGenerateCnmmDbSelectDbInfo" value="Odaberite jednu od baza podataka da biste generisali datoteku sa njenim opisom" />
  <sentence name="PxWebAdminToolsGenerateDbLanguageDependent" value="Ovisnost jezika" />
  <sentence name="PxWebAdminToolsGenerateDbLanguageDependentInfo" value="Prikaži sve datoteke bez obzira na odabrani jezik" />
  <sentence name="PxWebAdminToolsLanguageManagerSelectLanguage" value="--- Odaberite jezik ---" />
  <sentence name="PxWebAdminToolsLanguageManagerInfo" value="Odaberite jezik koji želite urediti. Ključ = Ključ koji identificira rečenicu u sistemu; Rezerva = Rečenica koja će se koristiti ako nema prevoda; Jezik = Rečenica u trenutno odabranom jeziku." />
  <sentence name="PxWebAdminToolsLanguageManagerSelectLanguageError" value="Morate izabrati jezik" />
  <sentence name="PxWebAdminToolsLanguageManagerKey" value="Ključ" />
  <sentence name="PxWebAdminToolsLanguageManagerFallback" value="Rezerva" />
  <sentence name="PxWebAdminToolsLanguageManagerLanguage" value="Jezik" />
  <sentence name="PxWebAdminToolsResetAll" value="Resetujte sve" />
  <sentence name="PxWebAdminToolsResetAllInfo" value="Resetujte sve statističke liste u PxWeb" />
  <sentence name="PxWebAdminToolsResetLanguage" value="Resetujte jezik" />
  <sentence name="PxWebAdminToolsResetLanguageInfo" value="Resetujte jezičku listu u sistemu jezika" />
  <sentence name="PxWebAdminToolsResetAggregation" value="Resetujte agregacije" />
  <sentence name="PxWebAdminToolsResetAggregationInfo" value="Oslobađa listu agregacija koje se učitane u memoriji" />
  <sentence name="PxWebAdminToolsResetDatabases" value="Resetujte bazu podataka" />
  <sentence name="PxWebAdminToolsResetDatabasesInfo" value="Resetuje spremljenu strukturu px baze podataka" />
  <sentence name="PxWebAdminToolsChangePasswordOld" value="Stara lozinka" />
  <sentence name="PxWebAdminToolsChangePasswordNew" value="Nova lozinka" />
  <sentence name="PxWebAdminToolsChangePasswordVerify" value="Provjerite novu lozinku" />
  <sentence name="PxWebAdminToolsChangePasswordChange" value="Promjena!" />
  <sentence name="PxWebAdminToolsChangePasswordWrongPassword" value="Pogrešna lozinka" />
  <sentence name="PxWebAdminToolsChangePasswordVerifyIncorrect" value="Provjerite netačno" />
  <sentence name="PxWebAdminToolsChangePasswordSuccess" value="Lozinka je promijenjena" />
  <sentence name="PxWebAdminFeaturesGeneralFeature" value="Mogućnost" />
  <sentence name="PxWebAdminFeaturesGeneralFeatureInfo" value="Odabrane mogućnosti će biti dostupne u administrativnim alatima i u PxWebu" />
  <sentence name="PxWebAdminFeaturesGeneralFeatureCharts" value="Grafikoni" />
  <sentence name="PxWebAdminFeaturesChartsGeneralChartSettings" value="Postavke grafikona" />
  <sentence name="PxWebAdminFeaturesChartsGeneralUserSettings" value="Početne vrijednosti za korisničke postavke" />
  <sentence name="PxWebAdminFeaturesChartsGeneralFontName" value="Naziv fonta" />
  <sentence name="PxWebAdminFeaturesChartsGeneralFontNameInfo" value="Font korišten u grafikonu" />
  <sentence name="PxWebAdminFeaturesChartsGeneralFontSizeTitle" value="Veličina fonta naslova" />
  <sentence name="PxWebAdminFeaturesChartsGeneralFontSizeTitleInfo" value="Veličina fonta naslova grafikona" />
  <sentence name="PxWebAdminFeaturesChartsGeneralFontSizeAxis" value="Veličina fonta na osi" />
  <sentence name="PxWebAdminFeaturesChartsGeneralFontSizeAxisInfo" value="Veličina fonta na osi grafikona" />
  <sentence name="PxWebAdminFeaturesChartsGeneralHeight" value="Visina" />
  <sentence name="PxWebAdminFeaturesChartsGeneralHeightInfo" value="Početna vrijednost korisničkih postavki za 'Visinu'" />
  <sentence name="PxWebAdminFeaturesChartsGeneralMaxHeight" value="Maksimalna visina" />
  <sentence name="PxWebAdminFeaturesChartsGeneralMaxHeightInfo" value="Visina grafikona ne može biti veća od ove vrijednosti" />
  <sentence name="PxWebAdminFeaturesChartsGeneralWidth" value="Širina" />
  <sentence name="PxWebAdminFeaturesChartsGeneralWidthInfo" value="Početna vrijednost korisničkih postavki za 'Širinu'" />
  <sentence name="PxWebAdminFeaturesChartsGeneralMaxWidth" value="Maksimalna širina" />
  <sentence name="PxWebAdminFeaturesChartsGeneralMaxWidthInfo" value="Širina grafikona ne može biti veća od ove vrijednosti" />
  <sentence name="PxWebAdminFeaturesChartsGeneralLineThickness" value="Debljina linije" />
  <sentence name="PxWebAdminFeaturesChartsGeneralLineThicknessInfo" value="Početna vrijednost korisničkih postavki za 'Debljinu linije'" />
  <sentence name="PxWebAdminFeaturesChartsGeneralMaxLineThickness" value="Maksimalna debljina linije" />
  <sentence name="PxWebAdminFeaturesChartsGeneralMaxLineThicknessInfo" value="Debljina linije ne može biti veća od ove vrijednosti" />
  <sentence name="PxWebAdminFeaturesChartsGeneralLabelOrientation" value="Orjentacija oznake" />
  <sentence name="PxWebAdminFeaturesChartsGeneralLabelOrientationHorizontal" value="Horizontalno" />
  <sentence name="PxWebAdminFeaturesChartsGeneralLabelOrientationVertical" value="Vertikalno" />
  <sentence name="PxWebAdminFeaturesChartsGeneralLabelOrientationInfo" value="Početna vrijednost korisničkih postavki za 'Orjentaciju oznake'" />
  <sentence name="PxWebAdminFeaturesChartsGeneralTimeSortOrder" value="Redosljed sortiranja vremena" />
  <sentence name="PxWebAdminFeaturesChartsGeneralTimeSortOrderAscending" value="Rastući" />
  <sentence name="PxWebAdminFeaturesChartsGeneralTimeSortOrderDescending" value="Opadajući" />
  <sentence name="PxWebAdminFeaturesChartsGeneralTimeSortOrderNone" value="Nijedan" />
  <sentence name="PxWebAdminFeaturesChartsGeneralTimeSortOrderInfo" value="Početna vrijednost korisničkih postavki za 'Sortiranje vremena'" />
  <sentence name="PxWebAdminFeaturesChartsGeneralShowLegend" value="Prikaži legendu" />
  <sentence name="PxWebAdminFeaturesChartsGeneralShowLegendInfo" value="Početna vrijednost korisničkih postavki za 'Prikaži legendu'" />
  <sentence name="PxWebAdminFeaturesChartsGeneralLegendHeight" value="Visina legende" />
  <sentence name="PxWebAdminFeaturesChartsGeneralLegendHeightInfo" value="Početna vrijednost korisničkih postavki za 'Visinu legende'" />
  <sentence name="PxWebAdminFeaturesChartsGeneralLegendFontSize" value="Veličina fonta legende" />
  <sentence name="PxWebAdminFeaturesChartsGeneralLegendFontSizeInfo" value="Veličina fonta legende grafikona" />
  <sentence name="PxWebAdminFeaturesChartsGeneralGuidelinesColor" value="Boja crte rešetke" />
  <sentence name="PxWebAdminFeaturesChartsGeneralGuidelinesColorInfo" value="Boja crta rešetke grafikona" />
  <sentence name="PxWebAdminFeaturesChartsGeneralGuidelinesHorizontal" value="Horizontalna crta rešetke" />
  <sentence name="PxWebAdminFeaturesChartsGeneralGuidelinesHorizontalInfo" value="Početna vrijednost korisničkih postavki za 'Horizontalnu crtu rešetke'" />
  <sentence name="PxWebAdminFeaturesChartsGeneralGuidelinesVertical" value="Vertikalna crta rešetke" />
  <sentence name="PxWebAdminFeaturesChartsGeneralGuidelinesVerticalInfo" value="Početna vrijednost korisničkih postavki za 'Vertikalnu crtu rešetke'" />
  <sentence name="PxWebAdminFeaturesChartsGeneralMaxValues" value="Maksimalni broj ćelija" />
  <sentence name="PxWebAdminFeaturesChartsGeneralMaxValuesInfo" value="Maksimalan broj ćelija (proizvod svih vrijednosti) koji se može odabrati prilikom stvaranja grafikona. Ako je odabrani broj ćelija veći od ove vrijednosti, grafikon neće biti prikazan. Svrha ove postavke je poštedjeti web server od stvaranja vrlo velikog grafikona koji uzima dosta snage računanja s web servera." />
  <sentence name="PxWebAdminFeaturesChartsGeneralColors" value="Boje" />
  <sentence name="PxWebAdminFeaturesChartsGeneralColorsInfo" value="Boje grafikona" />
  <sentence name="PxWebAdminFeaturesChartsGeneralAddColor" value="Dodaj boju" />
  <sentence name="PxWebAdminFeaturesChartsGeneralDeleteColor" value="Izbriši" />
  <sentence name="PxWebChartsSourceLabel" value="Izvor:" />
  <sentence name="PxWebChartsSource" value="Statistika Švedske" />
  <sentence name="PxWebAdminSettingsGeneralSiteApplicationName" value="Naziv aplikacije" />
  <sentence name="PxWebAdminSettingsGeneralSiteApplicationNameInfo" value="Naziv PxWeb instalacije" />
  <sentence name="PxWebAdminSettingsGeneralSiteLogoPath" value="Logo put" />
  <sentence name="PxWebAdminSettingsGeneralSiteLogoPathInfo" value="Ime datoteke slike" />
  <sentence name="PxWebAdminSettingsLanguageDefaultLanguage" value="Početni jezik" />
  <sentence name="PxWebAdminSettingsLanguageDefaultLanguageInfo" value="Početni jezik za PxWeb stranicu" />
  <sentence name="PxWebAdminSettingsLanguageSiteLanguages" value="Jezik" />
  <sentence name="PxWebAdminSettingsLanguageSiteLanguagesInfo" value="Odabrani jezik će biti dostupan na PxWeb stranici " />
  <sentence name="PxWebAdminSettingsLanguageDecimalSeparator" value="Decimalni razdvajač" />
  <sentence name="PxWebAdminSettingsLanguageDecimalSeparatorInfo" value="Znak za korištenje decimalnog razdvajanja" />
  <sentence name="PxWebAdminSettingsLanguageDecimalSeparatorPoint" value="Tačka" />
  <sentence name="PxWebAdminSettingsLanguageDecimalSeparatorComma" value="Zarez" />
  <sentence name="PxWebAdminSettingsLanguageThousandSeparator" value="Razdvajač hiljada" />
  <sentence name="PxWebAdminSettingsLanguageThousandSeparatorInfo" value="Znak za razdvajanje hiljada" />
  <sentence name="PxWebAdminSettingsLanguageThousandSeparatorNone" value="Nijedan" />
  <sentence name="PxWebAdminSettingsLanguageThousandSeparatorSpace" value="Prostor" />
  <sentence name="PxWebAdminSettingsLanguageThousandSeparatorPoint" value="Tačka" />
  <sentence name="PxWebAdminSettingsLanguageThousandSeparatorComma" value="Zarez" />
  <sentence name="PxWebAdminSettingsLanguageDateFormat" value="Format datuma" />
  <sentence name="PxWebAdminSettingsLanguageDateFormatInfo" value="Format korišten za datume" />
  <sentence name="PxWebAdminYes" value="Da" />
  <sentence name="PxWebAdminNo" value="Ne" />
  <sentence name="PxWebAdminConfirmSaveSettings" value="Da li želite sačuvati ove postavke?" />
  <sentence name="PxWebAdminConfirmGenerateDb" value="Da li želite generisati novu bazu podataka?" />
  <sentence name="PxWebAdminSettingsImplementedInComingVersions" value="Ova mogućnost će se provoditi u narednoj verziji PxWeb" />
</language>